MANIFEST.in
README.md
setup.py
unilyze/__init__.py
unilyze/create_cldr_dbs.py
unilyze/create_ucd_dbs.py
unilyze/unichar.py
unilyze/unistat.py
unilyze.egg-info/PKG-INFO
unilyze.egg-info/SOURCES.txt
unilyze.egg-info/dependency_links.txt
unilyze.egg-info/top_level.txt
unilyze/db/cldr_char_exemplar.json
unilyze/db/cldr_exemplar_char.json
unilyze/db/cldr_language_territory.json
unilyze/db/ucd_codepoints.json
unilyze/db/ucd_property_names.json
unilyze/db/ucd_property_values.json