Metadata-Version: 2.1
Name: unilyze
Version: 0.2.0
Summary: Get detailed unicode information about characters and text
Home-page: https://github.com/x821938/unilyze
Author: Alex Skov Jensen
Author-email: pydev@offline.dk
License: MIT
Project-URL: Documentation, https://github.com/x821938/unilyze
Project-URL: Source, https://github.com/x821938/unilyze
Keywords: unicode,codepoint,text,character,information,ucd,language,exemplar,cldr
Platform: UNKNOWN
Classifier: Programming Language :: Python :: 3
Classifier: Development Status :: 4 - Beta
Classifier: License :: OSI Approved :: MIT License
Classifier: Operating System :: OS Independent
Classifier: Topic :: Software Development :: Localization
Classifier: Topic :: Text Processing :: Filters
Classifier: Topic :: Text Processing :: General
Classifier: Topic :: Text Processing :: Linguistic
Classifier: Topic :: Text Editors :: Text Processing
Classifier: Intended Audience :: Developers
